thingsboard/__init__.py
thingsboard/monitor/__init__.py
thingsboard/monitor/app.py
thingsboard/monitor/endpoint.py
thingsboard/monitor/endpointobserver.py
thingsboard/monitor/endpointsupervisor.py
thingsboard/monitor/node.py
thingsboard/monitor/version.py
thingsboard_monitor-0.2.0.dist-info/licenses/LICENSE
thingsboard_monitor-0.2.0.dist-info/METADATA
thingsboard_monitor-0.2.0.dist-info/WHEEL
thingsboard_monitor-0.2.0.dist-info/top_level.txt
thingsboard_monitor-0.2.0.dist-info/RECORD
